aio_nookipedia-0.1.9.dist-info/licenses/LICENSE
aionookipedia/__init__.py
aionookipedia/client.py
aionookipedia/resources/__init__.py
aionookipedia/resources/events.py
aionookipedia/resources/recipe.py
aionookipedia/resources/villager.py
aionookipedia/resources/items/__init__.py
aionookipedia/resources/items/clothing.py
aionookipedia/resources/items/furniture.py
aionookipedia/resources/items/gyroid.py
aionookipedia/resources/items/interior_item.py
aionookipedia/resources/items/item.py
aionookipedia/resources/items/misc.py
aionookipedia/resources/items/photo.py
aionookipedia/resources/items/tool.py
aionookipedia/resources/museum/__init__.py
aionookipedia/resources/museum/artwork.py
aionookipedia/resources/museum/bug.py
aionookipedia/resources/museum/critter.py
aionookipedia/resources/museum/fish.py
aionookipedia/resources/museum/fossil.py
aionookipedia/resources/museum/sea_creature.py
aio_nookipedia-0.1.9.dist-info/METADATA
aio_nookipedia-0.1.9.dist-info/WHEEL
aio_nookipedia-0.1.9.dist-info/top_level.txt
aio_nookipedia-0.1.9.dist-info/RECORD
