Metadata-Version: 2.4
Name: aio-nookipedia
Version: 0.1.9
Summary: A simple, easy to use python wrapper for the Nookipedia API
Author: FormlessDuck
License-Expression: WTFPL
Classifier: Programming Language :: Python :: 3
Classifier: Operating System :: OS Independent
Requires-Python: >=3.13.7
License-File: LICENSE
Requires-Dist: aiohttp-client-cache
Dynamic: license-file
